torch_factorization_models/__init__.py
torch_factorization_models/implicit_mf.py
torch_factorization_models/losses.py
torch_factorization_models/mf_trainer.py
torch_factorization_models/movielens.py
torch_factorization_models/optimizers.py
torch_factorization_models-0.1.0.dist-info/LICENSE.md
torch_factorization_models-0.1.0.dist-info/WHEEL
torch_factorization_models-0.1.0.dist-info/METADATA
torch_factorization_models-0.1.0.dist-info/RECORD
